LICENSE
MANIFEST.in
README.md
setup.cfg
setup.py
djongo/__init__.py
djongo/admin.py
djongo/base.py
djongo/compiler.py
djongo/creation.py
djongo/cursor.py
djongo/database.py
djongo/exceptions.py
djongo/features.py
djongo/introspection.py
djongo/operations.py
djongo/schema.py
djongo/storage.py
djongo/transaction.py
djongo/models/__init__.py
djongo/models/fields.py
djongo/models/indexes.py
djongo/models/json.py
djongo/sql2mongo/__init__.py
djongo/sql2mongo/aggregation.py
djongo/sql2mongo/constraints.py
djongo/sql2mongo/converters.py
djongo/sql2mongo/functions.py
djongo/sql2mongo/operators.py
djongo/sql2mongo/query.py
djongo/sql2mongo/sql_tokens.py
djongo/sql2mongo/validation.py
djongox.egg-info/PKG-INFO
djongox.egg-info/SOURCES.txt
djongox.egg-info/dependency_links.txt
djongox.egg-info/requires.txt
djongox.egg-info/top_level.txt