Metadata-Version: 2.1
Name: djongox
Version: 1.3.6.3
Summary: Driver for allowing Django to use MongoDB as the database backend.
Home-page: https://www.djongomapper.com/
Author: doableware
Author-email: support@doableware.com
License: AGPL
Keywords: Django MongoDB driver connector
Platform: UNKNOWN
Classifier: Development Status :: 3 - Alpha
Classifier: Intended Audience :: Developers
Classifier: License :: OSI Approved :: BSD License
Classifier: Programming Language :: Python :: 3.6
Requires-Python: >=3.6
Provides-Extra: json
License-File: LICENSE
